jumpstarter_driver_tmt/__init__.py
jumpstarter_driver_tmt/client.py
jumpstarter_driver_tmt/driver.py
jumpstarter_driver_tmt/driver_test.py
jumpstarter_driver_tmt-0.7.4.dist-info/METADATA
jumpstarter_driver_tmt-0.7.4.dist-info/WHEEL
jumpstarter_driver_tmt-0.7.4.dist-info/RECORD
